odoo/addons/pos_cashback/README.rst
odoo/addons/pos_cashback/__init__.py
odoo/addons/pos_cashback/__manifest__.py
odoo/addons/pos_cashback/i18n/fr.po
odoo/addons/pos_cashback/i18n/it.po
odoo/addons/pos_cashback/i18n/pos_cashback.pot
odoo/addons/pos_cashback/readme/CONTRIBUTORS.rst
odoo/addons/pos_cashback/readme/DESCRIPTION.rst
odoo/addons/pos_cashback/readme/ROADMAP.rst
odoo/addons/pos_cashback/static/description/icon.png
odoo/addons/pos_cashback/static/description/index.html
odoo/addons/pos_cashback/static/description/pos_cashback_warning.png
odoo/addons/pos_cashback/static/src/js/models.esm.js
odoo/addons/pos_cashback/static/src/scss/pos_cashback.scss
odoo/addons/pos_cashback/static/src/xml/PaymentScreen/PaymentScreenStatus.xml
odoo_addon_pos_cashback-16.0.1.0.0.2.dist-info/METADATA
odoo_addon_pos_cashback-16.0.1.0.0.2.dist-info/WHEEL
odoo_addon_pos_cashback-16.0.1.0.0.2.dist-info/top_level.txt
odoo_addon_pos_cashback-16.0.1.0.0.2.dist-info/RECORD
